pytorch_merge/__init__.py
pytorch_merge/pytorch_merge.py
pytorch_merge-0.1.2.dist-info/LICENSE
pytorch_merge-0.1.2.dist-info/METADATA
pytorch_merge-0.1.2.dist-info/WHEEL
pytorch_merge-0.1.2.dist-info/entry_points.txt
pytorch_merge-0.1.2.dist-info/top_level.txt
pytorch_merge-0.1.2.dist-info/RECORD
