Metadata-Version: 2.1
Name: pytorch-merge
Version: 0.1.2
Summary: Merge LLM weights files that are split into multiple parts
Author-email: Donalda Feith <donaldafeith@gmail.com>
Maintainer-email: Donalda Feith <donaldafeith@gmail.com>, Stephen Karl Larroque <lrq3000@gmail.com>
License: GNU General Public License v3 or later
Project-URL: Homepage, https://github.com/donaldafeith/Pytorch_Merge
Project-URL: Documentation, https://github.com/donaldafeith/Pytorch_Merge/blob/master/README.md
Project-URL: Source, https://github.com/donaldafeith/Pytorch_Merge
Project-URL: Tracker, https://github.com/donaldafeith/Pytorch_Merge/issues
Project-URL: Download, https://github.com/donaldafeith/Pytorch_Merge/releases
Keywords: video,gestalt,movie,summary,summarization,thumbnails
Classifier: Development Status :: 3 - Alpha
Classifier: License :: OSI Approved :: GNU General Public License v3 or later (GPLv3+)
Classifier: Environment :: Console
Classifier: Operating System :: POSIX :: Linux
Classifier: Operating System :: MacOS :: MacOS X
Classifier: Operating System :: Microsoft :: Windows
Classifier: Environment :: Console
Classifier: Intended Audience :: Developers
Classifier: Intended Audience :: End Users/Desktop
Classifier: Intended Audience :: Information Technology
Classifier: Intended Audience :: System Administrators
Classifier: Programming Language :: Python
Classifier: Programming Language :: Python :: 3
Classifier: Programming Language :: Python :: 3.7
Classifier: Programming Language :: Python :: 3.8
Classifier: Programming Language :: Python :: 3.9
Classifier: Programming Language :: Python :: 3.10
Classifier: Programming Language :: Python :: 3.11
Classifier: Programming Language :: Python :: 3.12
Classifier: Programming Language :: Python :: Implementation :: PyPy
Classifier: Topic :: Scientific/Engineering :: Artificial Intelligence
Classifier: Topic :: Software Development :: Libraries
Classifier: Topic :: Software Development :: Libraries :: Python Modules
Classifier: Topic :: Utilities
Requires-Python: >=3.7
License-File: LICENSE
Requires-Dist: torch
Requires-Dist: transformers
Requires-Dist: tqdm
Provides-Extra: test
Requires-Dist: pytest ; extra == 'test'
Requires-Dist: pytest-cov ; extra == 'test'
Provides-Extra: testmeta
Requires-Dist: build ; extra == 'testmeta'
Requires-Dist: twine ; extra == 'testmeta'
Requires-Dist: validate-pyproject ; extra == 'testmeta'
